apantias/__init__.py
apantias/analysis.py
apantias/bin_to_h5.py
apantias/display.py
apantias/file_io.py
apantias/fitting.py
apantias/logger.py
apantias/params.py
apantias/standard.py
apantias/utils.py
apantias-2.0.2.dist-info/METADATA
apantias-2.0.2.dist-info/WHEEL
apantias-2.0.2.dist-info/licenses/LICENSE
apantias-2.0.2.dist-info/RECORD
