Metadata-Version: 2.4
Name: apantias
Version: 2.0.2
Summary: Tools for analysis of data from the DANAE experiment on HEPHY
Project-URL: Homepage, https://github.com/shakamaran/apantias
Project-URL: Issues, https://github.com/shakamaran/apantias/issues
Author-email: Florian Heinrich <florianheinrich@gmx.at>
License-File: LICENSE
Classifier: License :: OSI Approved :: MIT License
Classifier: Operating System :: OS Independent
Classifier: Programming Language :: Python :: 3
Requires-Python: <3.13,>=3.11
Requires-Dist: h5py
Requires-Dist: matplotlib
Requires-Dist: numba
Requires-Dist: numpy
Requires-Dist: scikit-learn
Requires-Dist: scipy
Requires-Dist: seaborn
